tp_shared/autoins_mpg_service/repos/autoins_results_stream_queue_repo.py
tp_shared/autoins_mpg_service/schemas/autoins_result_message.py
tp_shared/autoins_mpg_service/worker_services/base_autoins_results_stream_queue_worker_service.py
tp_shared/base/base_message.py
tp_shared/gibdd_service/repo/gibdd_dc_results_stream_queue_repo.py
tp_shared/gibdd_service/repo/gibdd_fine_results_stream_queue_repo.py
tp_shared/gibdd_service/schemas/gibdd_dc_result_message.py
tp_shared/gibdd_service/schemas/gibdd_fine_result_message.py
tp_shared/gibdd_service/worker_services/base_gibdd_dc_results_stream_queue_worker_service.py
tp_shared/gibdd_service/worker_services/base_gibdd_fine_results_stream_queue_worker_service.py
tp_shared/moneta_service/repo/moneta_charge_results_stream_queue_repo.py
tp_shared/moneta_service/schemas/moneta_charge_result_message.py
tp_shared/moneta_service/types/moneta_charge_status.py
tp_shared/mos_passes_service/repo/mos_passes_ovga_results_stream_queue_repo.py
tp_shared/mos_passes_service/repo/mos_passes_results_stream_queue_repo.py
tp_shared/mos_passes_service/schemas/mos_passes_ovga_result_message.py
tp_shared/mos_passes_service/schemas/mos_passes_result_message.py
tp_shared/mos_passes_service/types/mos_passes_service_types.py
tp_shared/mos_passes_service/worker_services/base_mos_passes_results_stream_queue_worker_service.py
tp_shared/nsis_service/repos/nsis_results_ack_list_queue_repo.py
tp_shared/nsis_service/schemas/nsis_result_message.py
tp_shared/nsis_service/types/nsis_task_type.py
tp_shared/nsis_service/worker_services/base_nsis_results_queue_worker_service.py
tp_shared/ocr_service/schemas/responses.py
tp_shared/ocr_service/types/ocr_doc_type.py
tp_shared/policies_service/repos/policies_event_stream_queue_repo.py
tp_shared/policies_service/schemas/policies_result_message.py
tp_shared/policies_service/worker_services/base_policies_results_queue_worker_service.py
tp_shared/rnis_check_service/repos/rnis_check_results_stream_queue_repo.py
tp_shared-0.2.432.dist-info/METADATA
tp_shared-0.2.432.dist-info/WHEEL
tp_shared-0.2.432.dist-info/RECORD
