Metadata-Version: 2.3
Name: tp-shared
Version: 0.2.432
Summary: 
Author: Developer
Author-email: front-gold@mail.ru
Requires-Python: >=3.12
Classifier: Programming Language :: Python :: 3
Classifier: Programming Language :: Python :: 3.12
Classifier: Programming Language :: Python :: 3.13
Requires-Dist: pydantic (>=2.11.7)
Requires-Dist: tp-helper (>=0.4.62,<0.5.0)
